{
    "classes": [
        {
            "className": "AppController",
            "lineNumber": 12,
            "methods": [
                {
                    "access": "public",
                    "arguments": [
                        {
                            "name": "launchProfileId",
                            "type": "QString"
                        }
                    ],
                    "index": 11,
                    "name": "startServer",
                    "returnType": "void"
                },
                {
                    "access": "public",
                    "index": 12,
                    "name": "stopServer",
                    "returnType": "void"
                },
                {
                    "access": "public",
                    "arguments": [
                        {
                            "name": "launchProfileId",
                            "type": "QString"
                        }
                    ],
                    "index": 13,
                    "name": "computeEffectiveProfile",
                    "returnType": "void"
                },
                {
                    "access": "public",
                    "index": 14,
                    "name": "clearLog",
                    "returnType": "void"
                },
                {
                    "access": "public",
                    "arguments": [
                        {
                            "name": "text",
                            "type": "QString"
                        }
                    ],
                    "index": 15,
                    "name": "copyToClipboard",
                    "returnType": "void"
                },
                {
                    "access": "public",
                    "index": 16,
                    "name": "installOfficialBinary",
                    "returnType": "void"
                },
                {
                    "access": "public",
                    "index": 17,
                    "name": "cancelOfficialBinaryInstall",
                    "returnType": "void"
                },
                {
                    "access": "public",
                    "arguments": [
                        {
                            "name": "launchProfileId",
                            "type": "QString"
                        }
                    ],
                    "index": 18,
                    "name": "smokeTestServer",
                    "returnType": "void"
                },
                {
                    "access": "public",
                    "index": 19,
                    "name": "smokeTestRunning",
                    "returnType": "bool"
                },
                {
                    "access": "public",
                    "arguments": [
                        {
                            "name": "binaryId",
                            "type": "QString"
                        },
                        {
                            "name": "flag",
                            "type": "QString"
                        }
                    ],
                    "index": 20,
                    "name": "resolveFlag",
                    "returnType": "QString"
                },
                {
                    "access": "public",
                    "index": 21,
                    "name": "version",
                    "returnType": "QString"
                }
            ],
            "object": true,
            "properties": [
                {
                    "constant": true,
                    "designable": true,
                    "final": false,
                    "index": 0,
                    "name": "binaryRegistry",
                    "read": "binaryRegistry",
                    "required": false,
                    "scriptable": true,
                    "stored": true,
                    "type": "BinaryRegistry*",
                    "user": false
                },
                {
                    "constant": true,
                    "designable": true,
                    "final": false,
                    "index": 1,
                    "name": "rootRegistry",
                    "read": "rootRegistry",
                    "required": false,
                    "scriptable": true,
                    "stored": true,
                    "type": "ModelRootRegistry*",
                    "user": false
                },
                {
                    "constant": true,
                    "designable": true,
                    "final": false,
                    "index": 2,
                    "name": "modelCatalog",
                    "read": "modelCatalog",
                    "required": false,
                    "scriptable": true,
                    "stored": true,
                    "type": "ModelCatalog*",
                    "user": false
                },
                {
                    "constant": true,
                    "designable": true,
                    "final": false,
                    "index": 3,
                    "name": "profileManager",
                    "read": "profileManager",
                    "required": false,
                    "scriptable": true,
                    "stored": true,
                    "type": "ProfileManager*",
                    "user": false
                },
                {
                    "constant": false,
                    "designable": true,
                    "final": false,
                    "index": 4,
                    "name": "serverRunning",
                    "notify": "serverRunningChanged",
                    "read": "serverRunning",
                    "required": false,
                    "scriptable": true,
                    "stored": true,
                    "type": "bool",
                    "user": false
                },
                {
                    "constant": false,
                    "designable": true,
                    "final": false,
                    "index": 5,
                    "name": "serverLog",
                    "notify": "serverLogChanged",
                    "read": "serverLog",
                    "required": false,
                    "scriptable": true,
                    "stored": true,
                    "type": "QString",
                    "user": false
                },
                {
                    "constant": false,
                    "designable": true,
                    "final": false,
                    "index": 6,
                    "name": "activeLaunchId",
                    "notify": "activeLaunchIdChanged",
                    "read": "activeLaunchId",
                    "required": false,
                    "scriptable": true,
                    "stored": true,
                    "type": "QString",
                    "user": false
                },
                {
                    "constant": false,
                    "designable": true,
                    "final": false,
                    "index": 7,
                    "name": "effectiveProfile",
                    "notify": "effectiveProfileChanged",
                    "read": "effectiveProfile",
                    "required": false,
                    "scriptable": true,
                    "stored": true,
                    "type": "QVariantMap",
                    "user": false
                },
                {
                    "constant": false,
                    "designable": true,
                    "final": false,
                    "index": 8,
                    "name": "needsSetup",
                    "notify": "setupStateChanged",
                    "read": "needsSetup",
                    "required": false,
                    "scriptable": true,
                    "stored": true,
                    "type": "bool",
                    "user": false
                },
                {
                    "constant": false,
                    "designable": true,
                    "final": false,
                    "index": 9,
                    "name": "installingOfficialBinary",
                    "notify": "installingOfficialBinaryChanged",
                    "read": "installingOfficialBinary",
                    "required": false,
                    "scriptable": true,
                    "stored": true,
                    "type": "bool",
                    "user": false
                },
                {
                    "constant": false,
                    "designable": true,
                    "final": false,
                    "index": 10,
                    "name": "officialBinaryInstallStatus",
                    "notify": "officialBinaryInstallStatusChanged",
                    "read": "officialBinaryInstallStatus",
                    "required": false,
                    "scriptable": true,
                    "stored": true,
                    "type": "QString",
                    "user": false
                },
                {
                    "constant": false,
                    "designable": true,
                    "final": false,
                    "index": 11,
                    "name": "officialBinaryInstallLog",
                    "notify": "officialBinaryInstallLogChanged",
                    "read": "officialBinaryInstallLog",
                    "required": false,
                    "scriptable": true,
                    "stored": true,
                    "type": "QString",
                    "user": false
                }
            ],
            "qualifiedClassName": "AppController",
            "signals": [
                {
                    "access": "public",
                    "index": 0,
                    "name": "serverRunningChanged",
                    "returnType": "void"
                },
                {
                    "access": "public",
                    "index": 1,
                    "name": "serverLogChanged",
                    "returnType": "void"
                },
                {
                    "access": "public",
                    "index": 2,
                    "name": "activeLaunchIdChanged",
                    "returnType": "void"
                },
                {
                    "access": "public",
                    "index": 3,
                    "name": "effectiveProfileChanged",
                    "returnType": "void"
                },
                {
                    "access": "public",
                    "index": 4,
                    "name": "setupStateChanged",
                    "returnType": "void"
                },
                {
                    "access": "public",
                    "index": 5,
                    "name": "installingOfficialBinaryChanged",
                    "returnType": "void"
                },
                {
                    "access": "public",
                    "index": 6,
                    "name": "officialBinaryInstallStatusChanged",
                    "returnType": "void"
                },
                {
                    "access": "public",
                    "index": 7,
                    "name": "officialBinaryInstallLogChanged",
                    "returnType": "void"
                },
                {
                    "access": "public",
                    "arguments": [
                        {
                            "name": "success",
                            "type": "bool"
                        },
                        {
                            "name": "message",
                            "type": "QString"
                        },
                        {
                            "name": "binaryPath",
                            "type": "QString"
                        }
                    ],
                    "index": 8,
                    "name": "officialBinaryInstallFinished",
                    "returnType": "void"
                },
                {
                    "access": "public",
                    "arguments": [
                        {
                            "name": "message",
                            "type": "QString"
                        }
                    ],
                    "index": 9,
                    "name": "serverError",
                    "returnType": "void"
                },
                {
                    "access": "public",
                    "arguments": [
                        {
                            "name": "passed",
                            "type": "bool"
                        },
                        {
                            "name": "output",
                            "type": "QString"
                        }
                    ],
                    "index": 10,
                    "name": "smokeTestFinished",
                    "returnType": "void"
                }
            ],
            "superClasses": [
                {
                    "access": "public",
                    "name": "QObject"
                }
            ]
        }
    ],
    "inputFile": "AppController.h",
    "outputRevision": 68
}
